MANIFEST.in
README.rst
setup.py
datalet/__init__.py
datalet.egg-info/PKG-INFO
datalet.egg-info/SOURCES.txt
datalet.egg-info/dependency_links.txt
datalet.egg-info/requires.txt
datalet.egg-info/top_level.txt
datalet/data/__init__.py
datalet/data/data_column.py
datalet/data/data_row.py
datalet/data/data_set.py
datalet/data/data_table.py
datalet/data/exceptions.py
datalet/data/validator.py
datalet/dependency/__init__.py
datalet/dependency/dependency.py
datalet/gui/Main.py
datalet/gui/__init__.py
datalet/logging/__init__.py
datalet/logging/logger.py
datalet/ml/__init__.py
datalet/ml/kmeans.py
datalet/olap/__init__.py
datalet/olap/client.py
datalet/olap/gateway_lanucher.py
datalet/olap/server.py
datalet/storage/__init__.py
datalet/storage/_utils.py
datalet/storage/bin_file_storage.py
datalet/storage/csv_storage.py
datalet/storage/db_types.py
datalet/storage/dbtable_storage.py
datalet/storage/eml_storage.py
datalet/storage/excel_storage.py
datalet/storage/excel_xls_storage.py
datalet/storage/excel_xlsx_storage.py
datalet/storage/exceptions.py
datalet/storage/facade.py
datalet/storage/file_storage.py
datalet/storage/html_storage.py
datalet/storage/storage.py
datalet/storage/storage_types.py
datalet/storage/temporarize.py
datalet/storage/text_file_storage.py
datalet/storage/tsv_storage.py
datalet/tools/__init__.py
datalet/tools/transfer.py
datalet/utils/__init__.py
datalet/utils/datetime_utils.py
datalet/utils/dict_utils.py
datalet/utils/encrypt_utils.py
datalet/utils/enum_utils.py
datalet/utils/file_utils.py
datalet/utils/inspect_utils.py
datalet/utils/list_utils.py
datalet/utils/regex_utils.py
datalet/utils/singleton_utils.py
datalet/utils/sql_utils.py
datalet/utils/str_utils.py
tests/__init__.py
tests/test_flow.py
tests/testing.py
tests/data/__init__.py
tests/data/test_data_column.py
tests/data/test_data_row.py
tests/data/test_data_table.py
tests/olap/FoodMart.xml
tests/olap/SystemSchema.xml
tests/storage/__init__.py
tests/storage/export_mysql_yueyuefa.py
tests/storage/export_mysql_yueyuefa_2.py
tests/storage/export_mysql_zhouzhouzhuan.py
tests/storage/export_mysql_zhouzhouzhuan_2.py
tests/storage/test_bin_file_storage.py
