Metadata-Version: 1.0
Name: datalet
Version: 0.8.0
Summary: datalet is a toolkit for data analysis.
Home-page: https://github.com/lipei86/datalet
Author: li pei
Author-email: pei@ilanever.com
License: UNKNOWN
Keywords: datalet
Platform: UNKNOWN
